dana/__init__.py
dana/api_client.py
dana/api_response.py
dana/exceptions.py
dana/rest.py
dana/base/__init__.py
dana/base/configuration.py
dana/base/model.py
dana/base/types.py
dana/disbursement/__init__.py
dana/disbursement/v1/__init__.py
dana/disbursement/v1/enum.py
dana/disbursement/v1/api/__init__.py
dana/disbursement/v1/api/disbursement_api.py
dana/disbursement/v1/models/__init__.py
dana/disbursement/v1/models/bank_account_inquiry_request.py
dana/disbursement/v1/models/bank_account_inquiry_request_additional_info.py
dana/disbursement/v1/models/bank_account_inquiry_response.py
dana/disbursement/v1/models/bank_account_inquiry_response_additional_info.py
dana/disbursement/v1/models/dana_account_inquiry_request.py
dana/disbursement/v1/models/dana_account_inquiry_request_additional_info.py
dana/disbursement/v1/models/dana_account_inquiry_response.py
dana/disbursement/v1/models/money.py
dana/disbursement/v1/models/transfer_to_bank_inquiry_status_request.py
dana/disbursement/v1/models/transfer_to_bank_inquiry_status_response.py
dana/disbursement/v1/models/transfer_to_bank_request.py
dana/disbursement/v1/models/transfer_to_bank_request_additional_info.py
dana/disbursement/v1/models/transfer_to_bank_response.py
dana/disbursement/v1/models/transfer_to_dana_inquiry_status_request.py
dana/disbursement/v1/models/transfer_to_dana_inquiry_status_response.py
dana/disbursement/v1/models/transfer_to_dana_request.py
dana/disbursement/v1/models/transfer_to_dana_request_additional_info.py
dana/disbursement/v1/models/transfer_to_dana_response.py
dana/merchant_management/__init__.py
dana/merchant_management/v1/__init__.py
dana/merchant_management/v1/enum.py
dana/merchant_management/v1/api/__init__.py
dana/merchant_management/v1/api/merchant_management_api.py
dana/merchant_management/v1/models/__init__.py
dana/merchant_management/v1/models/address_info.py
dana/merchant_management/v1/models/business_docs.py
dana/merchant_management/v1/models/create_division_request.py
dana_python-1.1.10.dist-info/licenses/LICENSE
dana_python-1.1.10.dist-info/METADATA
dana_python-1.1.10.dist-info/WHEEL
dana_python-1.1.10.dist-info/top_level.txt
dana_python-1.1.10.dist-info/RECORD
