Metadata-Version: 2.4
Name: dana-python
Version: 1.1.10
Summary: API Client (SDK) for DANA APIs based on https://dashboard.dana.id/api-docs
Author-email: DANA Package Manager  <package-manager@dana.id>
Maintainer-email: DANA Package Manager  <package-manager@dana.id>
License-Expression: Apache-2.0
Project-URL: homepage, https://dashboard.dana.id/api-docs
Project-URL: repository, https://github.com/dana-id/dana-python
Keywords: DANA,DANA ID Docs,DANA SDK,DANA Python,DANA API Client,DANA Python API Client,DANA Python SDK
Requires-Python: >3.9.1
License-File: LICENSE
Requires-Dist: annotated-types==0.7.0
Requires-Dist: cffi==1.17.1
Requires-Dist: cryptography<46.0.0,>=44.0.2
Requires-Dist: pycparser==2.22
Requires-Dist: pydantic<3.0.0,>=2.10.6
Requires-Dist: pydantic-core<3.0.0,>=2.27.2
Requires-Dist: python-dateutil==2.9.0.post0
Requires-Dist: six==1.17.0
Requires-Dist: typing-extensions<5.0.0,>=4.12.2
Requires-Dist: urllib3<3.0.0,>=2.3.0
Dynamic: license-file
